[{"title":"iOS App Distribution in 7 Steps","url":"http:\/\/developer.telerik.com\/featured\/ios-app-distribution-7-steps\/","source":"telerik.com"},{"title":"The Industrialisation of Design (or why Silicon Valley no longer needs UX designers)","url":"https:\/\/medium.com\/clear-left-thinking\/the-industrialisation-of-design-or-why-silicon-valley-no-longer-needs-ux-designers-dd11e022feaf#.9pqi93c9u","source":"medium.com"},{"title":"mapillary-js","url":"http:\/\/mapillary.github.io\/mapillary-js\/","source":"mapillary.github.io"},{"title":"With Accelerated Mobile Pages Coming This Month, Google Aims to Reinvent the Mobile Web","url":"http:\/\/adage.com\/article\/digital\/google-amp-launch-looms-search-engine-scores-follow\/302599\/","source":"adage.com"},{"title":"Google Ventures \u2013 Why you should move that button 3px to the left","url":"https:\/\/library.gv.com\/why-you-should-move-that-button-3px-to-the-left-c012e5ad32f7#.3bzz51fdd","source":"gv.com"},{"title":"ConvergeSE - April 13-15th 2016","url":"http:\/\/convergese.com\/","source":"convergese.com"}]