[{"title":"End of support for Internet Explorer 10 and older ","url":"https:\/\/www.microsoft.com\/en-us\/WindowsForBusiness\/End-of-IE-support","source":"microsoft.com"},{"title":"How to use UPSERT on Postgres 9.5 in practice","url":"http:\/\/blog.andrebarbosa.co\/upsert-on-postgres-9-5\/","source":"andrebarbosa.co"},{"title":"Top Python projects, tools and articles for 2015","url":"http:\/\/us4.campaign-archive2.com\/?u=9735795484d2e4c204da82a29&id=22fde1c28d&e=1c81d7b3e1","source":"campaign-archive2.com"}]