[{"title":"Rebooting the Automobile","url":"http:\/\/www.technologyreview.com\/featuredstory\/538446\/rebooting-the-automobile\/?src=longreads","source":"technologyreview.com"},{"title":"Why Aren't There More Women Futurists?","url":"http:\/\/www.theatlantic.com\/technology\/archive\/2015\/07\/futurism-sexism-men\/400097\/?src=longreads","source":"theatlantic.com"},{"title":"Dispossessed in the Land of Dreams","url":"https:\/\/newrepublic.com\/article\/124476\/dispossessed-land-dreams?src=longreads","source":"newrepublic.com"},{"title":"Longreads Best of 2015: Business & Tech","url":"http:\/\/blog.longreads.com\/2015\/12\/17\/longreads-best-of-2015-business-tech\/","source":"longreads.com"},{"title":"Taylor Wilson, Nuclear Boy Genius","url":"http:\/\/www.theguardian.com\/science\/2015\/jun\/20\/taylor-wilson-nuclear-teen-genius-science-interview?src=longreads","source":"theguardian.com"},{"title":"Who Owns Molecular Biology?","url":"https:\/\/bostonreview.net\/books-ideas\/yarden-katz-who-owns-molecular-biology?Src=longreads","source":"bostonreview.net"},{"title":"The Tech Elite\u2019s Quest to Reinvent School in Its Own Image","url":"http:\/\/www.wired.com\/2015\/10\/salman-khan-academy-lab-school-reinventing-classrooms\/?src=longreads","source":"wired.com"},{"title":"Get Up, Stand Up","url":"http:\/\/www.wired.com\/?p=1863721\/?Src=longreads","source":"wired.com"},{"title":"Hot Startup Theranos Has Struggled With Its Blood-Test Technology","url":"http:\/\/www.wsj.com\/articles\/theranos-has-struggled-with-blood-tests-1444881901","source":"wsj.com"},{"title":"A New Front","url":"https:\/\/story.californiasunday.com\/military-tech-silicon-valley?src=longreads","source":"californiasunday.com"}]