[{"title":"Analyze a Time Series in Real Time with AWS Lambda, Amazon Kinesis and Amazon DynamoDB Streams","url":"http:\/\/blogs.aws.amazon.com\/bigdata\/post\/Tx148NMGPIJ6F6F\/Analyze-a-Time-Series-in-Real-Time-with-AWS-Lambda-Amazon-Kinesis-and-Amazon-Dyn","source":"amazon.com"},{"title":"Churn Prediction with PySpark using MLlib and ML Packages","url":"https:\/\/www.mapr.com\/blog\/churn-prediction-pyspark-using-mllib-and-ml-packages","source":"mapr.com"},{"title":"DalmatinerDB","url":"https:\/\/github.com\/dalmatinerdb\/dalmatinerdb","source":"github.com"},{"title":"HDocDB","url":"https:\/\/github.com\/rayokota\/hdocdb","source":"github.com"},{"title":"Webinar: Continuous Applications: Spark, Kafka, Beam, and Beyond","url":"http:\/\/www.oreilly.com\/pub\/e\/3695","source":"oreilly.com"},{"title":"Webinar: Low-latency ingestion and analytics with Apache Kafka and Apache Apex (Hadoop)","url":"https:\/\/attendee.gotowebinar.com\/register\/6144492461887443972","source":"gotowebinar.com"},{"title":"Webinar: Data Modeling, Data Querying, and NoSQL: A Deep Dive","url":"http:\/\/www.oreilly.com\/pub\/e\/3694","source":"oreilly.com"},{"title":"Webinar: MongoDB and Analytics: Building Solutions with the MongoDB BI Connector","url":"https:\/\/www.mongodb.com\/webinar\/mongodb-and-analytics-building-solutions-with-the-mongodb-bi-connector","source":"mongodb.com"},{"title":"Building an Async Networking Layer for mongos","url":"https:\/\/engineering.mongodb.com\/post\/building-an-async-networking-layer-for-mongos\/","source":"mongodb.com"},{"title":"How to design an HBase data model for recommendations","url":"http:\/\/datacentric.pl\/blog\/2016\/03\/design-hbase-data-model-recommendations\/","source":"datacentric.pl"},{"title":"Getting Started with Couchbase and Spark on Apache Zeppelin","url":"http:\/\/blog.couchbase.com\/2016\/march\/getting-started-with-couchbase-and-spark-on-apache-zeppelin","source":"couchbase.com"},{"title":"Strong consistency in Manhattan","url":"https:\/\/blog.twitter.com\/2016\/strong-consistency-in-manhattan","source":"twitter.com"},{"title":"Financial Markets are Graphs","url":"https:\/\/www.youtube.com\/watch?v=U2VWd4fcSwM","source":"youtube.com"},{"title":"Using Neo4j to Take Us to the Stars","url":"http:\/\/neo4j.com\/blog\/neo4j-take-us-to-the-stars\/","source":"neo4j.com"},{"title":"Spark: Big Data Cluster Computing in Production","url":"http:\/\/amzn.to\/1MDg54K","source":"amzn.to"},{"title":"Chronicle-Map","url":"https:\/\/github.com\/OpenHFT\/Chronicle-Map","source":"github.com"},{"title":"mailcap","url":"https:\/\/github.com\/internalfx\/mailcap","source":"github.com"},{"title":"A tale of troubleshooting database performance, with Cassandra and sysdig","url":"http:\/\/www.planetcassandra.org\/blog\/a-tale-of-troubleshooting-database-performance-with-cassandra-and-sysdig\/","source":"planetcassandra.org"},{"title":"RDBMS & Graphs: Drivers for Connecting to a Graph Database","url":"http:\/\/neo4j.com\/blog\/rdbms-drivers-for-graph-database","source":"neo4j.com"},{"title":"DynamoDB Design Patterns and Best Practices","url":"https:\/\/www.youtube.com\/watch?v=PDQ3jbDyTQ4","source":"youtube.com"},{"title":"Redis Performance Monitoring with the ELK Stack","url":"http:\/\/logz.io\/blog\/redis-performance-monitoring-elk-stack\/","source":"logz.io"},{"title":"SASIIndex","url":"https:\/\/github.com\/apache\/cassandra\/blob\/trunk\/doc\/SASI.md","source":"github.com"}]