[{"title":"What's Coming Up for RethinkDB in 2016 [25 minutes]","url":"http:\/\/email.changelog.com\/t\/t-l-djydutk-l-jk\/","source":"changelog.com"},{"title":"Blocking Across The Wire (with JavaScript)","url":"http:\/\/email.changelog.com\/t\/t-l-djydutk-l-ju\/","source":"changelog.com"},{"title":"Ping The Changelog","url":"http:\/\/email.changelog.com\/t\/t-l-djydutk-l-tl\/","source":"changelog.com"},{"title":"Nancy","url":"http:\/\/email.changelog.com\/t\/t-l-djydutk-l-ti\/","source":"changelog.com"},{"title":"grell","url":"http:\/\/email.changelog.com\/t\/t-l-djydutk-l-td\/","source":"changelog.com"},{"title":"Scrapbook","url":"http:\/\/email.changelog.com\/t\/t-l-djydutk-l-th\/","source":"changelog.com"},{"title":"Realtime Infrastructure Monitoring","url":"http:\/\/email.changelog.com\/t\/t-l-djydutk-l-yk\/","source":"changelog.com"},{"title":"Slate","url":"http:\/\/email.changelog.com\/t\/t-l-djydutk-l-yu\/","source":"changelog.com"},{"title":"react-makes-you-sad","url":"http:\/\/email.changelog.com\/t\/t-l-djydutk-l-jr\/","source":"changelog.com"},{"title":"(\u256f\u00b0\u25a1\u00b0\uff09\u256f\ufe35 \u253b\u2501\u253b","url":"http:\/\/email.changelog.com\/t\/t-l-djydutk-l-jj\/","source":"changelog.com"},{"title":".dependencies","url":"http:\/\/email.changelog.com\/t\/t-l-djydutk-l-jt\/","source":"changelog.com"},{"title":"The Swift Algorithm Club!","url":"http:\/\/email.changelog.com\/t\/t-l-djydutk-l-ji\/","source":"changelog.com"},{"title":"Elm in Production [31 minutes]","url":"http:\/\/email.changelog.com\/t\/t-l-djydutk-l-jd\/","source":"changelog.com"},{"title":"Haskell Stack (Mega Tutorial) [2 hours]","url":"http:\/\/email.changelog.com\/t\/t-l-djydutk-l-jh\/","source":"changelog.com"},{"title":"Should You Learn Programming? Yes.","url":"http:\/\/email.changelog.com\/t\/t-l-djydutk-l-c\/","source":"changelog.com"},{"title":"The Difference Between Excellent, Good and Bad JavaScript Developers","url":"http:\/\/email.changelog.com\/t\/t-l-djydutk-l-a\/","source":"changelog.com"},{"title":"The Ultimate Robot Application Framework","url":"http:\/\/email.changelog.com\/t\/t-l-djydutk-l-f\/","source":"changelog.com"},{"title":"Swift Is Expanding Commit Access","url":"http:\/\/email.changelog.com\/t\/t-l-djydutk-l-z\/","source":"changelog.com"},{"title":"How to Deploy Software","url":"http:\/\/email.changelog.com\/t\/t-l-djydutk-l-v\/","source":"changelog.com"},{"title":"Flexbox Defense","url":"http:\/\/email.changelog.com\/t\/t-l-djydutk-l-e\/","source":"changelog.com"},{"title":"The Curious Case of the Issue and Pull Request Template","url":"http:\/\/email.changelog.com\/t\/t-l-djydutk-l-s\/","source":"changelog.com"},{"title":"Sensible Bash","url":"http:\/\/email.changelog.com\/t\/t-l-djydutk-l-w\/","source":"changelog.com"},{"title":"52 technologies in 2016","url":"http:\/\/email.changelog.com\/t\/t-l-djydutk-l-yh\/","source":"changelog.com"},{"title":"JavaScript Error Tracking Made Easy","url":"http:\/\/email.changelog.com\/t\/t-l-djydutk-l-k\/","source":"changelog.com"},{"title":"Java, Ruby, and Go, Oh My!","url":"http:\/\/email.changelog.com\/t\/t-l-djydutk-l-o\/","source":"changelog.com"},{"title":"Get Started With Versioning Large Files With Git Large File Storage","url":"http:\/\/email.changelog.com\/t\/t-l-djydutk-l-b\/","source":"changelog.com"},{"title":"Gists as npm Packages","url":"http:\/\/email.changelog.com\/t\/t-l-djydutk-l-n\/","source":"changelog.com"},{"title":"400Gbps of DDoS Attacks","url":"http:\/\/email.changelog.com\/t\/t-l-djydutk-l-p\/","source":"changelog.com"},{"title":"Free eBook on Continuous Integration\/Delivery with Docker","url":"http:\/\/email.changelog.com\/t\/t-l-djydutk-l-x\/","source":"changelog.com"},{"title":"What is \"the stack\"?","url":"http:\/\/email.changelog.com\/t\/t-l-djydutk-l-m\/","source":"changelog.com"},{"title":"Breaking The Fourth Wall In Software","url":"https:\/\/medium.com\/@alexbunardzic\/breaking-the-fourth-wall-in-software-d08a25df34b7#.sxf6s7esy","source":"medium.com"},{"title":"#197: The Future of WordPress and Calypso with Matt Mullenweg","url":"http:\/\/email.changelog.com\/t\/t-l-djydutk-l-y\/","source":"changelog.com"},{"title":"How DHH Organizes Rails Controllers","url":"http:\/\/email.changelog.com\/t\/t-l-djydutk-l-j\/","source":"changelog.com"},{"title":"We Need Software Engineers, Not Developers","url":"http:\/\/email.changelog.com\/t\/t-l-djydutk-l-i\/","source":"changelog.com"},{"title":"curl vs Wget","url":"http:\/\/email.changelog.com\/t\/t-l-djydutk-l-d\/","source":"changelog.com"}]