[{"title":"Web Engineering Manager at Slack","url":"http:\/\/email.jakebresnehan.com\/t\/r-l-evfhy-xiydriydk-jj\/","source":"jakebresnehan.com"},{"title":"Senior Product Designer at Charbeat","url":"http:\/\/email.jakebresnehan.com\/t\/r-l-evfhy-xiydriydk-jt\/","source":"jakebresnehan.com"},{"title":"Need to find passionate developers? Why not advertise in the next newsletter","url":"http:\/\/email.jakebresnehan.com\/t\/r-l-evfhy-xiydriydk-ji\/","source":"jakebresnehan.com"},{"title":"Performance & Usage at Instagram (engineering.instagram.com)","url":"http:\/\/email.jakebresnehan.com\/t\/r-l-evfhy-xiydriydk-jd\/","source":"jakebresnehan.com"},{"title":"A CSS Multi-column Layout Tutorial for Beginners","url":"http:\/\/email.jakebresnehan.com\/t\/r-l-evfhy-xiydriydk-s\/","source":"jakebresnehan.com"},{"title":"Facebook\u2019s Product Director Explains One of its Biggest UX Changes (fastcodesign.com)","url":"http:\/\/email.jakebresnehan.com\/t\/r-l-evfhy-xiydriydk-g\/","source":"jakebresnehan.com"},{"title":"Getting More from Google Analytics with Philip Walton (css-tricks.com)","url":"http:\/\/email.jakebresnehan.com\/t\/r-l-evfhy-xiydriydk-w\/","source":"jakebresnehan.com"},{"title":"CSS only Responsive Tables","url":"http:\/\/email.jakebresnehan.com\/t\/r-l-evfhy-xiydriydk-yd\/","source":"jakebresnehan.com"},{"title":"Rebass \u2014 56 Configurable React Stateless UI Components","url":"http:\/\/email.jakebresnehan.com\/t\/r-l-evfhy-xiydriydk-yh\/","source":"jakebresnehan.com"},{"title":"PostCSS.parts","url":"http:\/\/email.jakebresnehan.com\/t\/r-l-evfhy-xiydriydk-yk\/","source":"jakebresnehan.com"},{"title":"State of the art web development with React.js (github.com)","url":"http:\/\/email.jakebresnehan.com\/t\/r-l-evfhy-xiydriydk-yu\/","source":"jakebresnehan.com"},{"title":"The Difference Between Excellent, Good and Bad JavaScript Developers (thefullstack.xyz)","url":"http:\/\/email.jakebresnehan.com\/t\/r-l-evfhy-xiydriydk-jl\/","source":"jakebresnehan.com"},{"title":"Trellisheets \u2014 How we spin up CSS for Trello sites with ease (tech.trello.com)","url":"http:\/\/email.jakebresnehan.com\/t\/r-l-evfhy-xiydriydk-jr\/","source":"jakebresnehan.com"},{"title":"How to become a great UX designer without a degree (blog.invisionapp.com)","url":"http:\/\/email.jakebresnehan.com\/t\/r-l-evfhy-xiydriydk-jy\/","source":"jakebresnehan.com"},{"title":"Maybe we could tone down the JavaScript","url":"http:\/\/email.jakebresnehan.com\/t\/r-l-evfhy-xiydriydk-k\/","source":"jakebresnehan.com"},{"title":"What\u2019s New in jQuery 3 (developer.telerik.com)","url":"http:\/\/email.jakebresnehan.com\/t\/r-l-evfhy-xiydriydk-u\/","source":"jakebresnehan.com"},{"title":"Professional Logo Creation Kit","url":"http:\/\/email.jakebresnehan.com\/t\/r-l-evfhy-xiydriydk-b\/","source":"jakebresnehan.com"},{"title":"Design in a Sea of Engineering","url":"http:\/\/email.jakebresnehan.com\/t\/r-l-evfhy-xiydriydk-n\/","source":"jakebresnehan.com"},{"title":"Code for edge cases","url":"http:\/\/email.jakebresnehan.com\/t\/r-l-evfhy-xiydriydk-p\/","source":"jakebresnehan.com"},{"title":"Building Bixa Color, a color font for the web","url":"http:\/\/email.jakebresnehan.com\/t\/r-l-evfhy-xiydriydk-z\/","source":"jakebresnehan.com"},{"title":"Using D3.js with animations in React","url":"http:\/\/email.jakebresnehan.com\/t\/r-l-evfhy-xiydriydk-v\/","source":"jakebresnehan.com"},{"title":"Microcopy \u2014 Tiny Words with a Huge UX Impact","url":"http:\/\/email.jakebresnehan.com\/t\/r-l-evfhy-xiydriydk-e\/","source":"jakebresnehan.com"}]